Metadata-Version: 2.1
Name: netty
Version: 0.1
Summary: A simple python library for networking. Not extremely complex, but allows for simple game servers and chat rooms to be hosted.
Home-page: UNKNOWN
Author: Dexrey4 <https://github.com/dexrey4> and Enbyte Game Studios <https://github.com/enbyte>
License: UNKNOWN
Platform: UNKNOWN
Classifier: Programming Language :: Python :: 3
Classifier: License :: OSI Approved :: MIT License
Classifier: Operating System :: OS Independent
Requires-Python: >=3
License-File: LICENSE
